LICENSE
MANIFEST.in
README.md
setup.cfg
setup.py
elastic_vasp/__init__.py
elastic_vasp/art.py
elastic_vasp/average.py
elastic_vasp/coefficient.py
elastic_vasp/constants.py
elastic_vasp/elastic_gen.py
elastic_vasp/target.py
elastic_vasp.egg-info/PKG-INFO
elastic_vasp.egg-info/SOURCES.txt
elastic_vasp.egg-info/dependency_links.txt
elastic_vasp.egg-info/requires.txt
elastic_vasp.egg-info/top_level.txt
example/Cubic/INCAR
example/Cubic/KPOINTS
example/Cubic/POSCAR
example/Cubic/README
example/Cubic/copy.sh
example/Cubic/run.pbs
example/Cubic/strain.dat
example/Cubic/test.py
example/Hexagonal/INCAR
example/Hexagonal/KPOINTS
example/Hexagonal/POSCAR
example/Hexagonal/README
example/Hexagonal/copy.sh
example/Hexagonal/strain.dat
example/Hexagonal/test.py
example/Orthogonal/INCAR
example/Orthogonal/KPOINTS
example/Orthogonal/POSCAR
example/Orthogonal/README
example/Orthogonal/copy.sh
example/Orthogonal/run.pbs
example/Orthogonal/strain.dat
example/Orthogonal/test.py
example/Trigonal/INCAR
example/Trigonal/KPOINTS
example/Trigonal/POSCAR
example/Trigonal/README
example/Trigonal/copy.sh
example/Trigonal/run.pbs
example/Trigonal/strain.dat
example/Trigonal/test.py